investimentos/__init__.py
investimentos/investimentos.py
InvestPy_1st_attempt-0.1.dist-info/LICENSE
InvestPy_1st_attempt-0.1.dist-info/METADATA
InvestPy_1st_attempt-0.1.dist-info/WHEEL
InvestPy_1st_attempt-0.1.dist-info/top_level.txt
InvestPy_1st_attempt-0.1.dist-info/RECORD
